[
  {
    "id": "1",
    "name": "Emerald Silk Saree",
    "brand": "Saree Elegance",
    "images": [
      "https://new-sarees-bucket-speshway.s3.ap-south-1.amazonaws.com/uploads/1763973153328_product-1.jpg",
      "https://new-sarees-bucket-speshway.s3.ap-south-1.amazonaws.com/uploads/1763973153478_hero-saree-1.jpg",
      "https://new-sarees-bucket-speshway.s3.ap-south-1.amazonaws.com/uploads/1763973153540_hero-saree-2.jpg",
      "https://new-sarees-bucket-speshway.s3.ap-south-1.amazonaws.com/uploads/1763973153616_hero-saree-3.jpg",
      "https://new-sarees-bucket-speshway.s3.ap-south-1.amazonaws.com/uploads/1763973153672_1763620749145_600-TT11JUN27038.webp"
    ],
    "price": 12999,
    "originalPrice": 15999,
    "discount": 19,
    "colors": [
      "Emerald Green",
      "Gold"
    ],
    "fabrics": [
      "Pure Silk"
    ],
    "measurements": {
      "length": "6.3 meters",
      "width": "1.2 meters"
    },
    "care": "Dry clean only",
    "stock": 15,
    "rating": 4.5,
    "reviews": [
      {
        "id": "r1",
        "author": "Priya S.",
        "rating": 5,
        "comment": "Absolutely stunning saree! The silk quality is exceptional.",
        "date": "2024-01-15",
        "images": []
      },
      {
        "id": "1763720053377",
        "author": "user1@gmail.com",
        "rating": 4,
        "comment": "nice",
        "date": "2025-11-21",
        "images": [
          "https://new-sarees-bucket-speshway.s3.ap-south-1.amazonaws.com/uploads/1763973153767_1763720053360_product-4.jpg"
        ]
      }
    ],
    "category": "Silk Sarees",
    "occasion": "Wedding",
    "isBestSeller": false
  },
  {
    "id": "2",
    "name": "Royal Blue Banarasi",
    "brand": "Saree Elegance",
    "images": [
      "https://new-sarees-bucket-speshway.s3.ap-south-1.amazonaws.com/uploads/1763973153825_product-2.jpg",
      "https://new-sarees-bucket-speshway.s3.ap-south-1.amazonaws.com/uploads/1763973153869_hero-saree-2.jpg",
      "https://new-sarees-bucket-speshway.s3.ap-south-1.amazonaws.com/uploads/1763973153950_hero-saree-3.jpg"
    ],
    "price": 18999,
    "originalPrice": 22999,
    "discount": 17,
    "colors": [
      "Royal Blue",
      "Gold",
      "Silver"
    ],
    "fabrics": [
      "Banarasi Silk"
    ],
    "measurements": {
      "length": "6.3 meters",
      "width": "1.2 meters"
    },
    "care": "Dry clean only",
    "stock": 8,
    "rating": 4.9,
    "reviews": [
      {
        "id": "r2",
        "author": "Anjali K.",
        "rating": 5,
        "comment": "The zari work is breathtaking. Perfect for special occasions.",
        "date": "2024-01-20",
        "images": []
      }
    ],
    "category": "Banarasi Sarees",
    "occasion": "Festival",
    "isBestSeller": true,
    "onSale": false
  },
  {
    "id": "3",
    "name": "Pink Floral Silk",
    "brand": "Saree Elegance",
    "images": [
      "https://new-sarees-bucket-speshway.s3.ap-south-1.amazonaws.com/uploads/1763973154041_product-3.jpg",
      "https://new-sarees-bucket-speshway.s3.ap-south-1.amazonaws.com/uploads/1763973154082_hero-saree-1.jpg"
    ],
    "price": 9999,
    "originalPrice": 12999,
    "discount": 23,
    "colors": [
      "Pink",
      "Gold"
    ],
    "fabrics": [
      "Silk"
    ],
    "measurements": {
      "length": "6.3 meters",
      "width": "1.2 meters"
    },
    "care": "Dry clean only",
    "stock": 20,
    "rating": 4.7,
    "reviews": [],
    "category": "Silk Sarees",
    "occasion": "Party",
    "isBestSeller": false
  },
  {
    "id": "4",
    "name": "Maroon Kanjeevaram",
    "brand": "Saree Elegance",
    "images": [
      "https://new-sarees-bucket-speshway.s3.ap-south-1.amazonaws.com/uploads/1763973154128_product-4.jpg",
      "https://new-sarees-bucket-speshway.s3.ap-south-1.amazonaws.com/uploads/1763973154192_hero-saree-3.jpg"
    ],
    "price": 24999,
    "originalPrice": 29999,
    "discount": 17,
    "colors": [
      "Maroon",
      "Gold"
    ],
    "fabrics": [
      "Kanjeevaram Silk"
    ],
    "measurements": {
      "length": "6.3 meters",
      "width": "1.2 meters"
    },
    "care": "Dry clean only",
    "stock": 5,
    "rating": 5,
    "reviews": [
      {
        "id": "r3",
        "author": "Lakshmi M.",
        "rating": 5,
        "comment": "Heritage quality Kanjeevaram. Worth every rupee!",
        "date": "2024-01-25",
        "images": []
      }
    ],
    "category": "Kanjeevaram Sarees",
    "occasion": "Wedding"
  },
  {
    "id": "0962abea-1e78-4f7b-8bbc-4042432f68ae",
    "name": "new",
    "brand": "new",
    "images": [
      "https://new-sarees-bucket-speshway.s3.ap-south-1.amazonaws.com/uploads/1763973154292_1763445603502_product-4.jpg",
      "https://new-sarees-bucket-speshway.s3.ap-south-1.amazonaws.com/uploads/1763973154336_1763445603533_product-4.jpg",
      "https://new-sarees-bucket-speshway.s3.ap-south-1.amazonaws.com/uploads/1763973154376_1763445603533_hero-saree-3.jpg"
    ],
    "price": 12344,
    "discount": 23,
    "colors": [],
    "fabrics": [],
    "measurements": {
      "length": "",
      "width": ""
    },
    "care": "",
    "stock": 1,
    "rating": 0,
    "reviews": [],
    "category": "",
    "occasion": "",
    "onSale": false,
    "isBestSeller": true
  },
  {
    "id": "f6fb2462-d517-45a6-a615-84123b04e398",
    "name": "banaras",
    "brand": "banarass",
    "images": [
      "https://new-sarees-bucket-speshway.s3.ap-south-1.amazonaws.com/uploads/1763973154422_1763457624019_RA22126_zoom.jpg",
      "https://new-sarees-bucket-speshway.s3.ap-south-1.amazonaws.com/uploads/1763973154504_1763457624021_55555555555-500x500.webp",
      "https://new-sarees-bucket-speshway.s3.ap-south-1.amazonaws.com/uploads/1763973154557_1763457624023_44e1139b18c1059334a0158437ea53dc.jpg",
      "https://new-sarees-bucket-speshway.s3.ap-south-1.amazonaws.com/uploads/1763973154604_1763457624026_images__2_.jpg",
      "https://new-sarees-bucket-speshway.s3.ap-south-1.amazonaws.com/uploads/1763973154670_1763623413337_4479S205_1.webp",
      "https://new-sarees-bucket-speshway.s3.ap-south-1.amazonaws.com/uploads/1763973154769_1763623421849_3579S2516_3.webp"
    ],
    "price": 34322,
    "discount": 12,
    "colors": [],
    "fabrics": [],
    "measurements": {
      "length": "",
      "width": ""
    },
    "care": "",
    "stock": 55,
    "rating": 0,
    "reviews": [],
    "category": "Banarasi Sarees",
    "occasion": ""
  },
  {
    "id": "1617ee45-83d6-41cc-804c-c1a756066ecd",
    "name": "k",
    "brand": "m",
    "images": [
      "https://new-sarees-bucket-speshway.s3.ap-south-1.amazonaws.com/uploads/1763973154844_1763458042366_red-saree-golden-embroidery-mannequin-vibrant-intricate-draped-elegantly-traditional-garment-showcases-exquisite-391389281.webp"
    ],
    "price": 5555,
    "discount": 12,
    "colors": [],
    "fabrics": [],
    "measurements": {
      "length": "",
      "width": ""
    },
    "care": "",
    "stock": 4,
    "rating": 0,
    "reviews": [],
    "category": "Silk Sarees",
    "occasion": ""
  },
  {
    "id": "715c9bf2-acf3-418e-a648-eff6ead2c5af",
    "name": "n",
    "brand": "nm",
    "images": [
      "https://new-sarees-bucket-speshway.s3.ap-south-1.amazonaws.com/uploads/1763973154885_1763458225755_44e1139b18c1059334a0158437ea53dc.jpg"
    ],
    "price": 55522,
    "discount": 3,
    "colors": [],
    "fabrics": [],
    "measurements": {
      "length": "",
      "width": ""
    },
    "care": "",
    "stock": 4,
    "rating": 0,
    "reviews": [],
    "category": "Silk Sarees",
    "occasion": ""
  },
  {
    "id": "e939f54a-0953-4450-aaef-cdfa4043615b",
    "name": "kanchipuram",
    "brand": "hello",
    "images": [
      "https://new-sarees-bucket-speshway.s3.ap-south-1.amazonaws.com/uploads/1763973154958_1763628129290_3.webp",
      "https://new-sarees-bucket-speshway.s3.ap-south-1.amazonaws.com/uploads/1763973155025_1763628129322_44e1139b18c1059334a0158437ea53dc.jpg",
      "https://new-sarees-bucket-speshway.s3.ap-south-1.amazonaws.com/uploads/1763973155088_1763628129324_4479S205_1.webp",
      "https://new-sarees-bucket-speshway.s3.ap-south-1.amazonaws.com/uploads/1763973155205_1763628129336_red-saree-golden-embroidery-mannequin-vibrant-intricate-draped-elegantly-traditional-garment-showcases-exquisite-391389281.webp",
      "https://new-sarees-bucket-speshway.s3.ap-south-1.amazonaws.com/uploads/1763973155257_1763628129340_44e1139b18c1059334a0158437ea53dc.jpg"
    ],
    "price": 5999,
    "originalPrice": 6499,
    "discount": 20,
    "colors": [],
    "fabrics": [],
    "measurements": {
      "length": "",
      "width": ""
    },
    "care": "",
    "stock": 1,
    "rating": 3.3,
    "reviews": [
      {
        "id": "1763719013691",
        "author": "user3@gmail.com",
        "rating": 4,
        "comment": "awesome product ",
        "date": "2025-11-21",
        "images": [
          "https://new-sarees-bucket-speshway.s3.ap-south-1.amazonaws.com/uploads/1763973155302_1763719013672_hero-saree-3.jpg"
        ]
      },
      {
        "id": "1763720600548",
        "author": "user1@gmail.com",
        "rating": 3,
        "comment": "ok ",
        "date": "2025-11-21",
        "images": [
          "https://new-sarees-bucket-speshway.s3.ap-south-1.amazonaws.com/uploads/1763973155303_1763720600525_product-1.jpg"
        ]
      },
      {
        "id": "1763722292537",
        "author": "user1@gmail.com",
        "rating": 3,
        "comment": "not bad",
        "date": "2025-11-21",
        "images": [
          "https://new-sarees-bucket-speshway.s3.ap-south-1.amazonaws.com/uploads/1763973155304_1763722292480_hero-saree-3.jpg"
        ]
      }
    ],
    "category": "Lenin Ikkat",
    "occasion": "",
    "createdAt": 1763628129369,
    "onSale": true,
    "isBestSeller": true
  },
  {
    "id": "22484bfe-8241-4a85-8750-9f318d85de71",
    "name": "alsjfja",
    "brand": "",
    "images": [
      "https://new-sarees-bucket-speshway.s3.ap-south-1.amazonaws.com/uploads/1763972664196_product-1.jpg",
      "https://new-sarees-bucket-speshway.s3.ap-south-1.amazonaws.com/uploads/1763972664395_product-2.jpg",
      "https://new-sarees-bucket-speshway.s3.ap-south-1.amazonaws.com/uploads/1763972664479_hero-saree-1.jpg"
    ],
    "price": 43143,
    "originalPrice": 423423,
    "saveAmount": 1232,
    "discount": 23,
    "colors": [],
    "fabrics": [],
    "measurements": {
      "length": "",
      "width": ""
    },
    "care": "",
    "colorLinks": [],
    "stock": 1,
    "rating": 0,
    "reviews": [],
    "category": "Lenin Ikkat",
    "occasion": "",
    "createdAt": 1763972664560,
    "isBestSeller": false,
    "onSale": false
  }
]